Examples/alarms.py
Examples/all_controls.py
Examples/as_test.py
Examples/bbb_temperature.py
Examples/dashio_coms_module.py
Examples/dashio_test.py
Examples/dual_connection_TCP_DASH.py
Examples/event_log.py
Examples/ex00.py
Examples/ex01.py
Examples/ex02.py
Examples/ex03.py
Examples/ex04.py
Examples/ex05_SIM767X.py
Examples/map.py
Examples/system_monitor.py
Examples/tcp_example.py
Examples/time_graphs.py
Examples/RaspberryPi/TestBLE.py
Examples/RaspberryPi/ble_set_wifi.py
Examples/RaspberryPi/pi_sense_hat.py
Examples/RaspberryPi/pi_sense_hat_tsgraph.py
dashio/__init__.py
dashio/action_station.py
dashio/ble_connection.py
dashio/comms_module_connection.py
dashio/constants.py
dashio/dash_connection.py
dashio/device.py
dashio/ip.py
dashio/load_config.py
dashio/lte_767x_connection.py
dashio/mqtt_connection.py
dashio/py.typed
dashio/schedular.py
dashio/sim767x.py
dashio/tcp_connection.py
dashio/zeroconf_service.py
dashio/zmq_connection.py
dashio/action_station_services/__init__.py
dashio/action_station_services/action_station_service_config.py
dashio/action_station_services/as_servicel.py
dashio/action_station_services/clock_servicel.py
dashio/action_station_services/modbus_service.py
dashio/action_station_services/py.typed
dashio/action_station_services/task_service.py
dashio/action_station_services/timer_service.py
dashio/action_station_services/ttn_service.py
dashio/iotcontrol/__init__.py
dashio/iotcontrol/alarm.py
dashio/iotcontrol/audio_visual_display.py
dashio/iotcontrol/button.py
dashio/iotcontrol/button_group.py
dashio/iotcontrol/chart.py
dashio/iotcontrol/color_picker.py
dashio/iotcontrol/control.py
dashio/iotcontrol/device_view.py
dashio/iotcontrol/dial.py
dashio/iotcontrol/direction.py
dashio/iotcontrol/enums.py
dashio/iotcontrol/event.py
dashio/iotcontrol/event_log.py
dashio/iotcontrol/knob.py
dashio/iotcontrol/label.py
dashio/iotcontrol/map.py
dashio/iotcontrol/menu.py
dashio/iotcontrol/py.typed
dashio/iotcontrol/ring_buffer.py
dashio/iotcontrol/selector.py
dashio-3.5.10.dist-info/licenses/LICENSE
dashio-3.5.10.dist-info/METADATA
dashio-3.5.10.dist-info/WHEEL
dashio-3.5.10.dist-info/entry_points.txt
dashio-3.5.10.dist-info/top_level.txt
dashio-3.5.10.dist-info/RECORD
