Metadata-Version: 2.4
Name: dashio
Version: 3.5.10
Summary: DashIO interface library
Author-email: James Boulton <james@dashio.com>
License-Expression: MIT
Project-URL: Homepage, https://dashio.io
Project-URL: Repository, https://github.com/dashio-connect/python-dashio
Project-URL: Download, https://github.com/dashio-connect/python-dashio
Classifier: Programming Language :: Python :: 3.10
Classifier: Programming Language :: Python :: 3.11
Classifier: Programming Language :: Python :: 3.12
Classifier: Programming Language :: Python :: 3.13
Classifier: Operating System :: OS Independent
Requires-Python: >=3.10
License-File: LICENSE
Requires-Dist: paho-mqtt>=2.0.0
Requires-Dist: pyzmq
Requires-Dist: python-dateutil
Requires-Dist: zeroconf
Requires-Dist: shortuuid
Requires-Dist: pyserial
Provides-Extra: dev
Requires-Dist: pytest>=6.0; extra == "dev"
Requires-Dist: pytest-cov>=2.0; extra == "dev"
Requires-Dist: flake8>=3.9; extra == "dev"
Requires-Dist: tox>=4.0; extra == "dev"
Dynamic: license-file
